pydtl_relativepath/__init__.py
pydtl_relativepath/enums.py
pydtl_relativepath/pydtl_relativepath.py
pydtl_relativepath-0.2.0.dist-info/LICENSE
pydtl_relativepath-0.2.0.dist-info/METADATA
pydtl_relativepath-0.2.0.dist-info/WHEEL
pydtl_relativepath-0.2.0.dist-info/RECORD
