Metadata-Version: 2.1
Name: pydtl-relativepath
Version: 0.2.0
Summary: python tool to solve many issues with relative paths and imports in your complex framework.
Home-page: https://github.com/python-dev-tools/pydtl-relativepath
License: MIT
Keywords: relative path,absolute path,python,pydtl,python-dev-tools,poetry,pytest
Author: Nanthagopal-Eswaran
Author-email: nanthagopaleswaran@gmail.com
Maintainer: Nanthagopal-Eswaran
Maintainer-email: nanthagopaleswaran@gmail.com
Requires-Python: >=3.9,<4.0.0
Classifier: Development Status :: 5 - Production/Stable
Classifier: Intended Audience :: Developers
Classifier: License :: OSI Approved :: MIT License
Classifier: Operating System :: OS Independent
Classifier: Programming Language :: Python :: 3
Classifier: Programming Language :: Python :: 3.9
Classifier: Programming Language :: Python :: 3.10
Classifier: Programming Language :: Python :: 3.11
Classifier: Programming Language :: Python :: 3.12
Classifier: Programming Language :: Python :: 3 :: Only
Classifier: Topic :: Software Development
Classifier: Topic :: Software Development :: Build Tools
Classifier: Topic :: Software Development :: Libraries
Classifier: Topic :: Software Development :: Libraries :: Python Modules
Project-URL: Discussion, https://github.com/python-dev-tools/pydtl-relativepath/discussions
Project-URL: Repository, https://github.com/python-dev-tools/pydtl-relativepath
Project-URL: Source, https://github.com/python-dev-tools/pydtl-relativepath
Project-URL: Tracker, https://github.com/python-dev-tools/pydtl-relativepath/issues
